checksome/VERSION
checksome/__init__.py
checksome/__main__.py
checksome/checks.py
checksome/exceptions.py
checksome/logging.py
checksome/py.typed
checksome/reader.py
checksome/algorithms/__init__.py
checksome/algorithms/algorithm.py
checksome/algorithms/py.typed
checksome/algorithms/sha256.py
checksome/cli/__init__.py
checksome/cli/args.py
checksome/cli/checksome_cli.py
checksome/cli/checksome_task.py
checksome/cli/py.typed
checksome-1.0.0.dist-info/LICENSE
checksome-1.0.0.dist-info/METADATA
checksome-1.0.0.dist-info/WHEEL
checksome-1.0.0.dist-info/entry_points.txt
checksome-1.0.0.dist-info/top_level.txt
checksome-1.0.0.dist-info/RECORD
